{
    "labels": [
        {
            "label_type": "box", 
            "label_class": "donbe", 
            "centre": {
                "y": 355.0, 
                "x": 105.71428571428572
            }, 
            "object_id": 1, 
            "size": {
                "y": 168.09523809523807, 
                "x": 113.80952380952381
            }
        }, 
        {
            "label_type": "box", 
            "label_class": "donbe", 
            "centre": {
                "y": 532.6190476190476, 
                "x": 154.04761904761904
            }, 
            "object_id": 2, 
            "size": {
                "y": 157.61904761904765, 
                "x": 114.28571428571428
            }
        }, 
        {
            "label_type": "box", 
            "label_class": "noodle", 
            "centre": {
                "y": 228.33333333333331, 
                "x": 105.23809523809524
            }, 
            "object_id": 3, 
            "size": {
                "y": 78.57142857142856, 
                "x": 52.85714285714285
            }
        }, 
        {
            "label_type": "box", 
            "label_class": "noodle", 
            "centre": {
                "y": 213.33333333333331, 
                "x": 173.8095238095238
            }, 
            "object_id": 4, 
            "size": {
                "y": 86.66666666666663, 
                "x": 66.1904761904762
            }
        }, 
        {
            "label_type": "box", 
            "label_class": "noodle", 
            "centre": {
                "y": 251.19047619047618, 
                "x": 315.4761904761905
            }, 
            "object_id": 5, 
            "size": {
                "y": 105.23809523809524, 
                "x": 94.28571428571428
            }
        }, 
        {
            "label_type": "box", 
            "label_class": "miso_soup", 
            "centre": {
                "y": 81.9047619047619, 
                "x": 206.1904761904762
            }, 
            "object_id": 6, 
            "size": {
                "y": 80.95238095238096, 
                "x": 61.428571428571416
            }
        }, 
        {
            "label_type": "box", 
            "label_class": "miso_soup", 
            "centre": {
                "y": 166.9047619047619, 
                "x": 272.3809523809524
            }, 
            "object_id": 7, 
            "size": {
                "y": 90.00000000000001, 
                "x": 75.71428571428572
            }
        }, 
        {
            "label_type": "box", 
            "label_class": "miso_soup", 
            "centre": {
                "y": 133.57142857142856, 
                "x": 374.04761904761904
            }, 
            "object_id": 8, 
            "size": {
                "y": 102.38095238095238, 
                "x": 95.23809523809524
            }
        }
    ], 
    "complete": null, 
    "image_filename": "donbe_ssd_image32.jpg"
}